{
  "title": "Human consciousness itself is a simulation recreatable in AI",
  "url": "https://x.com/Plinz/status/1512691329012101120",
  "date": "2022-04-09",
  "excerpt": "I think that human consciousness is itself a simulation, and one that can eventually be recreated in important aspects by AI models. If we give the AI system an identity born out of a continuous experience of the interaction between world and motivated self, its art becomes real.",
  "source_host": "x.com",
  "handle": "Plinz",
  "thread_id": null
}